{
    "configuration": [
        {
            "PartitionKey": "websitemon_func",
            "RowKey": "ping",
            "websiteUrl": "https://quackajack.wordpress.com/"
        },
        {
            "PartitionKey": "websitemon_func",
            "RowKey": "alert_webhook",
            "websiteUrl": "https://hooks.slack.com/services/abcd/efgh/12345678"

        },
        {
            "PartitionKey": "websitemon_func",
            "RowKey": "logon",
            "websiteUrl": "https://example.com/signIn",
            "usernameField": "Username",
            "passwordField": "Password"
        }
    ]
}